setup.py
python_probability/Binomialdistribution.py
python_probability/Gaussiandistribution.py
python_probability/Generaldistribution.py
python_probability/__init__.py
python_probability.egg-info/PKG-INFO
python_probability.egg-info/SOURCES.txt
python_probability.egg-info/dependency_links.txt
python_probability.egg-info/not-zip-safe
python_probability.egg-info/top_level.txt